cvapipe_analysis/__init__.py
cvapipe_analysis/bin/__init__.py
cvapipe_analysis/steps/__init__.py
cvapipe_analysis/steps/aggregation/__init__.py
cvapipe_analysis/steps/aggregation/aggregation.py
cvapipe_analysis/steps/aggregation/aggregation_tools.py
cvapipe_analysis/steps/cellpack/__init__.py
cvapipe_analysis/steps/cellpack/cellpack.py
cvapipe_analysis/steps/cellpack/cellpack_tools.py
cvapipe_analysis/steps/compute_features/__init__.py
cvapipe_analysis/steps/compute_features/compute_features.py
cvapipe_analysis/steps/compute_features/compute_features_tools.py
cvapipe_analysis/steps/concordance/__init__.py
cvapipe_analysis/steps/concordance/concordance.py
cvapipe_analysis/steps/concordance/concordance_tools.py
cvapipe_analysis/steps/correlation/__init__.py
cvapipe_analysis/steps/correlation/correlation.py
cvapipe_analysis/steps/correlation/correlation_tools.py
cvapipe_analysis/steps/load_data/__init__.py
cvapipe_analysis/steps/load_data/load_data.py
cvapipe_analysis/steps/load_data/load_data_tools.py
cvapipe_analysis/steps/parameterization/__init__.py
cvapipe_analysis/steps/parameterization/parameterization.py
cvapipe_analysis/steps/parameterization/parameterization_tools.py
cvapipe_analysis/steps/preprocessing/__init__.py
cvapipe_analysis/steps/preprocessing/filtering_tools.py
cvapipe_analysis/steps/preprocessing/outliers_tools.py
cvapipe_analysis/steps/preprocessing/preprocessing.py
cvapipe_analysis/steps/shapemode/__init__.py
cvapipe_analysis/steps/shapemode/shapemode.py
cvapipe_analysis/steps/shapemode/shapemode_tools.py
cvapipe_analysis/steps/stereotypy/__init__.py
cvapipe_analysis/steps/stereotypy/stereotypy.py
cvapipe_analysis/steps/stereotypy/stereotypy_tools.py
cvapipe_analysis/steps/validation/__init__.py
cvapipe_analysis/steps/validation/validation.py
cvapipe_analysis/steps/validation/validation_tools.py
cvapipe_analysis/tools/__init__.py
cvapipe_analysis/tools/cluster.py
cvapipe_analysis/tools/controller.py
cvapipe_analysis/tools/general.py
cvapipe_analysis-0.2.0.dist-info/LICENSE
cvapipe_analysis-0.2.0.dist-info/METADATA
cvapipe_analysis-0.2.0.dist-info/WHEEL
cvapipe_analysis-0.2.0.dist-info/top_level.txt
cvapipe_analysis-0.2.0.dist-info/RECORD
