Metadata-Version: 2.1
Name: cvapipe_analysis
Version: 0.2.0
Summary: Analysis pipeline usinf in Integrated intracellular organization and its variations in human iPS cells
Home-page: https://github.com/AllenCellModeling/cvapipe_analysis
Author: Matheus Viana
Author-email: matheus.viana@alleninstitute.org
License: Allen Institute Software License
Keywords: cvapipe_analysis
Classifier: Development Status :: 5 - Production/Stable
Classifier: Intended Audience :: Science/Research
Classifier: License :: Free for non-commercial use
Classifier: Natural Language :: English
Classifier: Programming Language :: Python :: 3 :: Only
Requires-Python: >=3.9
License-File: LICENSE
Requires-Dist: jupyter
Requires-Dist: aicsshparam
Requires-Dist: aicscytoparam
Provides-Extra: all
Requires-Dist: jupyter ; extra == 'all'
Requires-Dist: aicsshparam ; extra == 'all'
Requires-Dist: aicscytoparam ; extra == 'all'
Requires-Dist: pytest-runner >=5.2 ; extra == 'all'
Requires-Dist: black ; extra == 'all'
Requires-Dist: flake8 ; extra == 'all'
Requires-Dist: flake8-debugger ; extra == 'all'
Requires-Dist: pytest ; extra == 'all'
Requires-Dist: pytest-cov ; extra == 'all'
Requires-Dist: pytest-raises ; extra == 'all'
Requires-Dist: bump2version ; extra == 'all'
Requires-Dist: coverage ; extra == 'all'
Requires-Dist: ipython ; extra == 'all'
Requires-Dist: m2r2 ; extra == 'all'
Requires-Dist: pytest-runner ; extra == 'all'
Requires-Dist: sphinx ; extra == 'all'
Requires-Dist: furo ; extra == 'all'
Requires-Dist: tox ; extra == 'all'
Requires-Dist: twine ; extra == 'all'
Requires-Dist: wheel ; extra == 'all'
Provides-Extra: dev
Requires-Dist: pytest-runner >=5.2 ; extra == 'dev'
Requires-Dist: black ; extra == 'dev'
Requires-Dist: flake8 ; extra == 'dev'
Requires-Dist: flake8-debugger ; extra == 'dev'
Requires-Dist: pytest ; extra == 'dev'
Requires-Dist: pytest-cov ; extra == 'dev'
Requires-Dist: pytest-raises ; extra == 'dev'
Requires-Dist: bump2version ; extra == 'dev'
Requires-Dist: coverage ; extra == 'dev'
Requires-Dist: ipython ; extra == 'dev'
Requires-Dist: m2r2 ; extra == 'dev'
Requires-Dist: pytest-runner ; extra == 'dev'
Requires-Dist: sphinx ; extra == 'dev'
Requires-Dist: furo ; extra == 'dev'
Requires-Dist: tox ; extra == 'dev'
Requires-Dist: twine ; extra == 'dev'
Requires-Dist: wheel ; extra == 'dev'
Provides-Extra: setup
Requires-Dist: pytest-runner >=5.2 ; extra == 'setup'
Provides-Extra: test
Requires-Dist: black ; extra == 'test'
Requires-Dist: flake8 ; extra == 'test'
Requires-Dist: flake8-debugger ; extra == 'test'
Requires-Dist: pytest ; extra == 'test'
Requires-Dist: pytest-cov ; extra == 'test'
Requires-Dist: pytest-raises ; extra == 'test'
